hydro/__init__.py
hydro/hello.py
test/__init__.py
test/test_hello.py
owenhydrodemo-0.0.1.dist-info/LICENSE
owenhydrodemo-0.0.1.dist-info/METADATA
owenhydrodemo-0.0.1.dist-info/WHEEL
owenhydrodemo-0.0.1.dist-info/top_level.txt
owenhydrodemo-0.0.1.dist-info/RECORD
